{
  "stats": {
    "minecraft:dropped": {
      "bren:netherite_shotgun": 1
    },
    "minecraft:picked_up": {
      "bren:netherite_shotgun": 1
    },
    "minecraft:custom": {
      "minecraft:sprint_one_cm": 1456,
      "minecraft:time_since_rest": 378,
      "minecraft:walk_one_cm": 861,
      "minecraft:total_world_time": 378,
      "minecraft:fly_one_cm": 1858,
      "minecraft:play_time": 378,
      "minecraft:jump": 7,
      "minecraft:time_since_death": 378,
      "minecraft:drop": 1
    }
  },
  "DataVersion": 4775
}