{
  "stats": {
    "minecraft:dropped": {
      "bren:auto_gun": 1
    },
    "minecraft:custom": {
      "minecraft:sprint_one_cm": 5926,
      "minecraft:time_since_rest": 795,
      "minecraft:walk_one_cm": 617,
      "minecraft:total_world_time": 837,
      "minecraft:leave_game": 1,
      "minecraft:fly_one_cm": 5084,
      "minecraft:walk_under_water_one_cm": 659,
      "minecraft:walk_on_water_one_cm": 545,
      "minecraft:play_time": 795,
      "minecraft:jump": 17,
      "minecraft:time_since_death": 795,
      "minecraft:drop": 1
    },
    "minecraft:picked_up": {
      "bren:auto_gun": 1
    }
  },
  "DataVersion": 4786
}