{
  "stats": {
    "minecraft:custom": {
      "minecraft:sprint_one_cm": 4129,
      "minecraft:time_since_rest": 1045,
      "minecraft:walk_one_cm": 1145,
      "minecraft:total_world_time": 1052,
      "minecraft:leave_game": 1,
      "minecraft:fly_one_cm": 7131,
      "minecraft:play_time": 1045,
      "minecraft:jump": 20,
      "minecraft:time_since_death": 1045,
      "minecraft:drop": 1
    },
    "minecraft:picked_up": {
      "bren:netherite_tactical_auto_gun": 1,
      "minecraft:string": 2,
      "minecraft:spider_eye": 1
    },
    "minecraft:dropped": {
      "bren:netherite_tactical_auto_gun": 1
    }
  },
  "DataVersion": 4786
}